<?xml version="1.0" encoding="UTF-8"?>

<PropertyList>

  <!-- Le fuselage -->
  <model>
    <path>Aircraft/AR-234/Models/ar234.xml</path>
    <offsets>
      <x-m>  0 </x-m>
      <y-m>  0 </y-m>
      <z-m>  0 </z-m>
      <pitch-deg> 0 </pitch-deg>
    </offsets>
  </model>

  <!-- Les roues -->
  <model>
    <path>Aircraft/AR-234/Models/wheels.xml</path>
    <offsets>
      <x-m>  0 </x-m>
      <y-m>  0 </y-m>
      <z-m>  0 </z-m>
      <pitch-deg> 0 </pitch-deg>
    </offsets>
  </model>

  <!-- Les moteurs supplémentaires -->
  <model>
    <path>Aircraft/AR-234/Models/engines.xml</path>
    <offsets>
      <x-m>  0 </x-m>
      <y-m>  0 </y-m>
      <z-m>  0 </z-m>
      <pitch-deg> 0 </pitch-deg>
    </offsets>
  </model>

  <!-- Une ombre pour OSG -->
  <model>
    <name>shadowOSG</name>
    <path>Aircraft/AR-234/Models/shadowC.xml</path>
  </model>

  <animation>
    <type>select</type>
    <object-name>shadowOSG</object-name>
    <condition>
      <equals>
        <property>sim[0]/rendering/shadows-ai</property>
        <value>true</value>
      </equals>
    </condition>
  </animation>

</PropertyList>
